{
    "wildFeature": [
      { "name": "a Crevasse, rock, ice or lava across your path", "heightModifier": -1 },
      { "name": "a Crevasse, rock, ice or lava parallel to your path", "heightModifier": -1 },
      { "name": "a Cave or sinkhole: rock, ice or lava", "heightModifier": -1 },
      { "name": "a Steep slope up ", "heightModifier": 0.5 },
      { "name": "a Steep slope down", "heightModifier": -0.5 },
      { "name": "a Peak", "heightModifier": 1 },
      { "name": "the base of a Cliff", "heightModifier": 1 },
      { "name": "the edge of Cliff", "heightModifier": -1 },
      { "name": "Boulders or other broken ground", "heightModifier": 0.2 },
      { "name": "some brush and heather", "heightModifier": 0.1 },
      { "name": "a dense grove of firs", "heightModifier": 0.4 },
      { "name": "a medium stand of trees", "heightModifier": 0.2 },
      { "name": "a Ridgeline across your path", "heightModifier": 0.5 },
      { "name": "a Ridgeline parallel to your path", "heightModifier": 0.5 },
      { "name": "a Gully across your path", "heightModifier": -0.3 },
      { "name": "a Gully parallel to your path", "heightModifier": -0.3 },
      { "name": "a River or water course, parallel to your path", "heightModifier": -0.1 },
      { "name": "a River or water course, across your path", "heightModifier": -0.1 },
      { "name": "a treacherous surface or ice and wet rocks" },
      { "name": "a drift of deep snow" },
      { "name": "a Bridge", "heightModifier": 0.1 },
      { "name": "a Ruin", "areaModifier": 0.5, "heightModifier": 0.3 },
      { "name": "a lone Building", "areaModifier": 0.5, "heightModifier": 0.2 },
      { "name": "a Monument", "areaModifier": 0.1, "heightModifier": 0.1 },
      { "name": "a hotspring" },
      { "name": "raised ground, a hill or outcrop", "heightModifier": 0.4 },
      { "name": "a Crossroad", "areaModifier": 0.1 },
      { "name": "a Mountain Pass", "heightModifier": 0.6 },
      { "name": "a Sheltered Bay", "heightModifier": -0.1 },
      { "name": "a ford River crossing", "heightModifier": -0.1 },
      { "name": "where 2 Rivers meet", "heightModifier": -0.1 },
      { "name": "a open mine working", "areaModifier": 0.2 },
      { "name": "a standing stone marking ley lines", "areaModifier": 0.1 },
      { "name": "a hidden resting place, hard to find", "areaModifier": -0.1 }

  ]
  }
 